mdiicons/__init__.py
mdiicons/mdiicons.py
mdiicons-0.0.2.dist-info/METADATA
mdiicons-0.0.2.dist-info/WHEEL
mdiicons-0.0.2.dist-info/top_level.txt
mdiicons-0.0.2.dist-info/RECORD
