Metadata-Version: 2.1
Name: mdiicons
Version: 0.0.2
Summary: Material Design SVG strings for Python
Home-page: https://github.com/Patrick762/mdiicons
Author: Patrick762
Author-email: <pip-mdi-icons@hosting-rt.de>
Keywords: python,mdi,materialdesign,material design,materialdesignicons,material design icons,icons
Classifier: Development Status :: 1 - Planning
Classifier: Intended Audience :: Developers
Classifier: Programming Language :: Python :: 3
Classifier: Operating System :: Unix
Classifier: Operating System :: MacOS :: MacOS X
Classifier: Operating System :: Microsoft :: Windows
